{"noMoreComments": true, "cursorEnd": 0, "id": "2840938", "comments": [{"postBy": {"location": "\u9ad8\u96c4\u5e02\u00b7\u53f0\u7063", "utc": 1451869525000, "level": 0, "avatar": "http://filestoresg1.beetalkmobile.com:8081/file/687105712978771846", "name": "\u963f\u6cf0.."}, "content": "\u904e\u5e74\u7684\u6dfa\u8349\u5bfa(\u4e8c)", "urls": [], "replies": {"first": [], "last": [], "noMoreReplies": true}, "images": ["http://filestoresg1.beetalkmobile.com:8081/file/96c8cddaa0d1bd7b467fd9a52376b3ef", "http://filestoresg1.beetalkmobile.com:8081/file/5b612df7cc0cb54bee1f81048028f01f", "http://filestoresg1.beetalkmobile.com:8081/file/10533213e2884d0aae22d2d7b994f5e9", "http://filestoresg1.beetalkmobile.com:8081/file/4c0f2c3a11aff31d40e074a29ae94c7a", "http://filestoresg1.beetalkmobile.com:8081/file/44af927e17b3ea574d1cc5f42d5e1b3c", "http://filestoresg1.beetalkmobile.com:8081/file/bcc655d52e1d280a9fba3591deb1dc89"], "id": 28485255}, {"postBy": {"location": "\u9ad8\u96c4\u5e02\u00b7\u53f0\u7063", "utc": 1451955242000, "level": 0, "avatar": "http://filestoresg1.beetalkmobile.com:8081/file/687105712978771846", "name": "\u963f\u6cf0.."}, "content": "\u904e\u5e74\u7684\u6dfa\u8349\u5bfa(\u4e09)", "urls": [], "replies": {"first": [], "last": [], "noMoreReplies": true}, "images": ["http://filestoresg1.beetalkmobile.com:8081/file/e9ec49884a548e6399f0ca789b74ed02", "http://filestoresg1.beetalkmobile.com:8081/file/23eef4a1f466143847415155258eb597", "http://filestoresg1.beetalkmobile.com:8081/file/cb7e8fdfb8138e282f1cb3c6376dfee0", "http://filestoresg1.beetalkmobile.com:8081/file/e7747e0adf3efc92217f7081eb337237", "http://filestoresg1.beetalkmobile.com:8081/file/201630a63c47aba458ae1e567f2a48c2", "http://filestoresg1.beetalkmobile.com:8081/file/83fea91a29ff3f236bfda5bb8dbf0595"], "id": 28551921}, {"postBy": {"location": "\u9ad8\u96c4\u5e02\u00b7\u53f0\u7063", "utc": 1452214236000, "level": 0, "avatar": "http://filestoresg1.beetalkmobile.com:8081/file/-7044993206671946945", "name": " \ud83c\udf38JC\ud83c\udf38 "}, "content": "\u662f\u4eca\u5e74\u7684\u7167\u7247\u55ce?", "urls": [], "replies": {"first": [{"content": "\u662f\u7684\u662f\u4eca\u5e74\u5143\u65e6\u904e\u5e74\u7684\u7167\u7247", "reply": "", "id": 18397044, "name": "\u963f\u6cf0.."}], "last": [{"content": "\u6211\u4e5f\u5728\u90a3\u8de8\u5e74....", "reply": "\u963f\u6cf0..", "id": 18400493, "name": " \ud83c\udf38JC\ud83c\udf38 "}, {"content": "\u662f\u5594\uff01\u771f\u5de7\uff0c \u4e0d\u8a8d\u8b58\u59b3\u4e0d\u7136\u5c31\u53ef\u4ee5\u53bb\u627e\u59b3", "reply": "", "id": 18403628, "name": "\u963f\u6cf0.."}], "noMoreReplies": true}, "images": [], "id": 28768574}, {"postBy": {"location": "", "utc": 1452675966000, "level": 0, "avatar": "http://filestoresg1.beetalkmobile.com:8081/file/-936118696928467744", "name": "\u963f\u6d69"}, "content": "\u5f88\u71b1\u9b27\u5466 \u4e5f\u5f88\u4e7e\u6de8", "urls": [], "replies": {"first": [], "last": [], "noMoreReplies": true}, "images": [], "id": 29167212}, {"postBy": {"location": "\u65b0\u5317\u5e02\u00b7\u53f0\u7063", "utc": 1452952152000, "level": 0, "avatar": "http://filestoresg1.beetalkmobile.com:8081/file/6971269867253827239", "name": "\u52a0\u8cf4\u7684\u5225\u52a0\u6211\u5c0f\u9716\u54aa\u5a1c"}, "content": "\u771f\u71b1\u9b27", "urls": [], "replies": {"first": [], "last": [], "noMoreReplies": true}, "images": [], "id": 29412908}]}
