{"noMoreComments": true, "cursorEnd": 0, "id": "2802754", "comments": [{"postBy": {"location": "\u5609\u7fa9\u7e23\u00b7\u53f0\u7063", "utc": 1451391783000, "level": 0, "avatar": "http://filestoresg1.beetalkmobile.com:8081/file/1518729038731172328", "name": "\u5433\u739f\u4fe1"}, "content": "\u592a\u6f02\u4eae\u4e86", "urls": [], "replies": {"first": [], "last": [], "noMoreReplies": true}, "images": ["http://filestoresg1.beetalkmobile.com:8081/file/89c777f80c43a575e24c2f043358c9c9"], "id": 28140134}, {"postBy": {"location": "\u5f70\u5316\u7e23\u00b7\u53f0\u7063", "utc": 1451522965000, "level": 0, "avatar": "http://filestoresg1.beetalkmobile.com:8081/file/-568670696653903672", "name": "\u982d\u6bbc\u58de\u6389"}, "content": "\u53ef\u4ee5\u505a\u500b\u670b\u53cb", "urls": [], "replies": {"first": [], "last": [], "noMoreReplies": true}, "images": [], "id": 28238561}, {"postBy": {"location": "\u65b0\u5317\u5e02\u00b7\u53f0\u7063", "utc": 1458468147000, "level": 0, "avatar": "http://filestoresg1.beetalkmobile.com:8081/file/-5856225424617648600", "name": "\u6200\u5152"}, "content": "\u6de1\u6c34+1   \u8981\u51fa\u4f86\u559d\u5496\u5561\u804a\u662f\u975e\u55ce\uff1f", "urls": [], "replies": {"first": [], "last": [], "noMoreReplies": true}, "images": [], "id": 34410854}, {"postBy": {"location": "\u65b0\u5317\u5e02\u00b7\u53f0\u7063", "utc": 1458483645000, "level": 0, "avatar": "http://filestoresg1.beetalkmobile.com:8081/file/583050126621245440", "name": "\u5e78\u798f\u4eba\u59bb"}, "content": "\u4e0d\u662f\u6de1\u6c34ok\u561b", "urls": [], "replies": {"first": [], "last": [], "noMoreReplies": true}, "images": [], "id": 34430407}, {"postBy": {"location": "\u65b0\u5317\u5e02\u00b7\u53f0\u7063", "utc": 1458752496000, "level": 0, "avatar": "http://filestoresg1.beetalkmobile.com:8081/file/-4300926632255842809", "name": "\u5b89\u742a\u7f8e\u9aee\u5e2b"}, "content": "\u6de1\u6c34+1", "urls": [], "replies": {"first": [], "last": [], "noMoreReplies": true}, "images": [], "id": 34695840}, {"postBy": {"location": "\u53f0\u5317\u5e02\u00b7\u53f0\u7063", "utc": 1460530269000, "level": 0, "avatar": "http://filestoresg1.beetalkmobile.com:8081/file/-2945212313526355567", "name": "\ud83d\ude4f"}, "content": "\u6de1\u6c34\u6709\u9ede\u9060", "urls": [], "replies": {"first": [], "last": [], "noMoreReplies": true}, "images": [], "id": 36377744}]}
