{"noMoreComments": true, "cursorEnd": 0, "id": "2344471", "comments": [{"postBy": {"location": "\u53f0\u4e2d\u5e02\u00b7\u53f0\u7063", "utc": 1445135637000, "level": 0, "avatar": "http://filestoresg1.beetalkmobile.com:8081/file/-8099417154513068321", "name": "\u4e0d\u73a9\u4e86\u2026\u2026\u4e00\u9031\u5f8c\u522a"}, "content": "\u65e9\u2026\u2026", "urls": [], "replies": {"first": [{"content": "\u5348\u5b89\uff5e\uff5e\uff5e", "reply": "", "id": 14456394, "name": "\ud83d\udc3e\u5c0f\u53ef\u611b\ud83d\udc0a"}], "last": [{"content": "\u55ef\u55ef\uff5e\uff5e\u8def\u4e0a\u5c0f\u5fc3\u5537", "reply": "", "id": 14456991, "name": "\ud83d\udc3e\u5c0f\u53ef\u611b\ud83d\udc0a"}, {"content": "\u6069\u6069\u2026\u2026\u59b3\u4e5f\u5feb\u53bb\u5403\u5427", "reply": "\ud83d\udc3e\u5c0f\u53ef\u611b\ud83d\udc0a", "id": 14457039, "name": "\u4e0d\u73a9\u4e86\u2026\u2026\u4e00\u9031\u5f8c\u522a"}], "noMoreReplies": false}, "images": [], "id": 22828332}, {"postBy": {"location": "\u53f0\u5357\u5e02\u00b7\u53f0\u7063", "utc": 1445135690000, "level": 0, "avatar": "http://filestoresg1.beetalkmobile.com:8081/file/-886400983571469434", "name": "LIN  CHIHCHAN"}, "content": "\u597d\u53ef\u7231\uff01", "urls": [], "replies": {"first": [{"content": "\u8b1d\u8b1d\u5537", "reply": "", "id": 14456398, "name": "\ud83d\udc3e\u5c0f\u53ef\u611b\ud83d\udc0a"}], "last": [], "noMoreReplies": true}, "images": [], "id": 22828379}, {"postBy": {"location": "\u53f0\u4e2d\u5e02\u00b7\u53f0\u7063", "utc": 1445136274000, "level": 0, "avatar": "http://filestoresg1.beetalkmobile.com:8081/file/4585762841886881093", "name": "\u6b50\u5409\u5361"}, "content": "\u65e9 \u65e9 \u65e9", "urls": [], "replies": {"first": [{"content": "\u5348\u5b89\uff5e\uff5e  \u3124\u3124", "reply": "", "id": 14456413, "name": "\ud83d\udc3e\u5c0f\u53ef\u611b\ud83d\udc0a"}], "last": [], "noMoreReplies": true}, "images": [], "id": 22828903}, {"postBy": {"location": "\u6843\u5712\u5e02\u00b7\u53f0\u7063", "utc": 1445136368000, "level": 0, "avatar": "http://filestoresg1.beetalkmobile.com:8081/file/-8990270072595769568", "name": "\u767d"}, "content": "\u65e9\u554a", "urls": [], "replies": {"first": [{"content": "\u5348\u5b89\u554a\uff01\uff01", "reply": "", "id": 14456421, "name": "\ud83d\udc3e\u5c0f\u53ef\u611b\ud83d\udc0a"}, {"content": "\ud83d\ude00\ud83d\ude00", "reply": "", "id": 14463686, "name": "\u767d"}], "last": [], "noMoreReplies": true}, "images": [], "id": 22829007}, {"postBy": {"location": "", "utc": 1445136494000, "level": 0, "avatar": "http://filestoresg1.beetalkmobile.com:8081/file/-244710830465922163", "name": "\u963f\u6bdb"}, "content": "\u65e9\u5b89", "urls": [], "replies": {"first": [{"content": "\u5348\u5b89", "reply": "", "id": 14456426, "name": "\ud83d\udc3e\u5c0f\u53ef\u611b\ud83d\udc0a"}, {"content": "\u73fe\u5728\u662f\u4e0b\u5348\u8336\u6642\u9593\u56c9", "reply": "", "id": 14468366, "name": "\u963f\u6bdb"}], "last": [], "noMoreReplies": true}, "images": [], "id": 22829138}, {"postBy": {"location": "\u6843\u5712\u5e02\u00b7\u53f0\u7063", "utc": 1445137308000, "level": 0, "avatar": "http://filestoresg1.beetalkmobile.com:8081/file/-3811393284600691899", "name": "\u5c0f\u7ff0\u5152"}, "content": "\u4e00\u5b9a\u8981\u63a8\u4e00\u4e0b\u7684\u554a~", "urls": [], "replies": {"first": [{"content": "\u54c8\uff01   \u63a8\u63a8\u63a8", "reply": "", "id": 14456436, "name": "\ud83d\udc3e\u5c0f\u53ef\u611b\ud83d\udc0a"}], "last": [], "noMoreReplies": true}, "images": [], "id": 22829954}, {"postBy": {"location": "\u57fa\u9686\u5e02\u00b7\u53f0\u7063", "utc": 1445139159000, "level": 0, "avatar": "http://filestoresg1.beetalkmobile.com:8081/file/-6753988765873828863", "name": "\ud83d\udc7b\ud83d\udc7b"}, "content": "\ud83d\ude46\ud83d\ude47\ud83d\ude46\ud83d\ude47\ud83d\ude46\ud83d\ude47\ud83d\ude46\ud83d\ude47", "urls": [], "replies": {"first": [{"content": "\u54c8\u54c8\uff01\u6709\u6897", "reply": "", "id": 14456452, "name": "\ud83d\udc3e\u5c0f\u53ef\u611b\ud83d\udc0a"}, {"content": "\u8fc5\u901f\u819c\u62dc\ud83d\ude38", "reply": "\ud83d\udc3e\u5c0f\u53ef\u611b\ud83d\udc0a", "id": 14456472, "name": "\ud83d\udc7b\ud83d\udc7b"}], "last": [], "noMoreReplies": true}, "images": [], "id": 22831996}, {"postBy": {"location": "\u53f0\u5357\u5e02\u00b7\u53f0\u7063", "utc": 1445139829000, "level": 0, "avatar": "http://filestoresg1.beetalkmobile.com:8081/file/-4998104974314092372", "name": "\u53ef\u7b11\u7684app"}, "content": "\u4e2d\u5348\u4e86\uff0c\u5348\u5b89", "urls": [], "replies": {"first": [{"content": "\u5348\u5b89", "reply": "", "id": 14456456, "name": "\ud83d\udc3e\u5c0f\u53ef\u611b\ud83d\udc0a"}], "last": [{"content": "\u6069\uff0c\u5403\u98ef\u6642\u9593\u5230\u4e86\uff0c\u5c0f\u53ef\u611b\uff0c\u53bb\u5403\u98ef\u5427\uff0c\uff0c\uff0c\u795d\u6709\u500b\u958b\u5fc3\u5348\u9910\uff0c\uff0c\uff0c", "reply": "\ud83d\udc3e\u5c0f\u53ef\u611b\ud83d\udc0a", "id": 14456527, "name": "\u53ef\u7b11\u7684app"}, {"content": "\u771f\u6e96\u6642", "reply": "", "id": 14456583, "name": "\ud83d\udc3e\u5c0f\u53ef\u611b\ud83d\udc0a"}], "noMoreReplies": true}, "images": [], "id": 22832740}, {"postBy": {"location": "\u53f0\u4e2d\u5e02\u00b7\u53f0\u7063", "utc": 1445140311000, "level": 0, "avatar": "http://filestoresg1.beetalkmobile.com:8081/file/2238402276715837423", "name": "\u4fca\u826f"}, "content": "\u4f86\u54e5\u54e5\u62b1\u62b1\uff01", "urls": [], "replies": {"first": [{"content": "\ud83d\ude01\ud83d\ude01\ud83d\ude01", "reply": "", "id": 14456461, "name": "\ud83d\udc3e\u5c0f\u53ef\u611b\ud83d\udc0a"}], "last": [], "noMoreReplies": true}, "images": [], "id": 22833260}, {"postBy": {"location": "\u65b0\u5317\u5e02\u00b7\u53f0\u7063", "utc": 1445140481000, "level": 0, "avatar": "http://filestoresg1.beetalkmobile.com:8081/file/1", "name": "\u8d85\u60e1\u7537\u5b50"}, "content": "\u90a3\u88e1\u53ef\u611b\u4e86", "urls": [], "replies": {"first": [{"content": "\u6bcf\u500b\u4eba\u7684\u53ef\u611b\u5b9a\u7fa9\u4e0d\u4e00\u6a23\u3002  \u4f60\u4e5f\u53ef\u4ee5\u53ef\u611b\u5440\uff5e", "reply": "", "id": 14456487, "name": "\ud83d\udc3e\u5c0f\u53ef\u611b\ud83d\udc0a"}, {"content": "\u6211\u662f\u8001\u7070\u963f\u4e86\uff0c\u53ef\u611b\u5c31\u7d66\u5e74\u8f15\u4eba\u5427", "reply": "", "id": 14461005, "name": "\u8d85\u60e1\u7537\u5b50"}], "last": [], "noMoreReplies": true}, "images": ["http://filestoresg1.beetalkmobile.com:8081/file/df2592855872e7c165a2febb0ea75772"], "id": 22833455}, {"postBy": {"location": "\u53f0\u4e2d\u5e02\u00b7\u53f0\u7063", "utc": 1445141438000, "level": 0, "avatar": "http://filestoresg1.beetalkmobile.com:8081/file/-3373522197032206336", "name": "\u8292\u679c\u4e4b\u795e"}, "content": "\u5348\u5b89\u54e6", "urls": [], "replies": {"first": [], "last": [], "noMoreReplies": true}, "images": [], "id": 22834527}, {"postBy": {"location": "\u82b1\u84ee\u7e23\u00b7\u53f0\u7063", "utc": 1445148832000, "level": 0, "avatar": "http://filestoresg1.beetalkmobile.com:8081/file/4165263410171919885", "name": "\u4f86\u81ea\u661f\u661f\u7684\u6211"}, "content": "\u5348\u5b89\u4e86", "urls": [], "replies": {"first": [], "last": [], "noMoreReplies": true}, "images": [], "id": 22842867}, {"postBy": {"location": "\u53f0\u4e2d\u5e02\u00b7\u53f0\u7063", "utc": 1445189588000, "level": 0, "avatar": "http://filestoresg1.beetalkmobile.com:8081/file/-3373522197032206336", "name": "\u8292\u679c\u4e4b\u795e"}, "content": "\u53ef\u611b\u5594<br />\u53ef\u4ee5\u52a0\u597d\u53cb\u55ce", "urls": [], "replies": {"first": [], "last": [], "noMoreReplies": true}, "images": [], "id": 22894988}, {"postBy": {"location": "\u5c4f\u6771\u7e23\u00b7\u53f0\u7063", "utc": 1445194664000, "level": 0, "avatar": "http://filestoresg1.beetalkmobile.com:8081/file/5492144145064039170", "name": "\u720d"}, "content": "\u6703\u4e0d\u6703\u526a\u4e00\u526a\u8b8a\u8981\u5243\u5149\u982d\uff1f", "urls": [], "replies": {"first": [], "last": [], "noMoreReplies": true}, "images": [], "id": 22898824}, {"postBy": {"location": "\u9ad8\u96c4\u5e02\u00b7\u53f0\u6e7e", "utc": 1445195092000, "level": 0, "avatar": "http://filestoresg1.beetalkmobile.com:8081/file/35120610987006196", "name": "Dr. Rabbit"}, "content": "\u8b1d\u5b89\uff0c\u53ef\u4ee5\u9000\u4e0b\u4e86\uff0c\u6715\u9084\u60f3\u4f11\u606f", "urls": [], "replies": {"first": [], "last": [], "noMoreReplies": true}, "images": [], "id": 22899056}, {"postBy": {"location": "\u65b0\u5317\u5e02\u00b7\u53f0\u7063", "utc": 1445219788000, "level": 0, "avatar": "http://filestoresg1.beetalkmobile.com:8081/file/-1231512392617550466", "name": "\u99ac\u514b\u767d"}, "content": "\u8dea\u5b89\u5427", "urls": [], "replies": {"first": [], "last": [], "noMoreReplies": true}, "images": [], "id": 22910496}, {"postBy": {"location": "\u6843\u5712\u5e02\u00b7\u53f0\u7063", "utc": 1445221860000, "level": 0, "avatar": "http://filestoresg1.beetalkmobile.com:8081/file/6730336085103170304", "name": "\u963f\u5049"}, "content": "\u65e9\u5b89\u554a", "urls": [], "replies": {"first": [], "last": [], "noMoreReplies": true}, "images": [], "id": 22912330}]}
