{"noMoreComments": true, "cursorEnd": 0, "id": "2371123", "comments": [{"postBy": {"location": "\u53f0\u5357\u5e02\u00b7\u53f0\u7063", "utc": 1445447064000, "level": 0, "avatar": "http://filestoresg1.beetalkmobile.com:8081/file/-6503992806560294302", "name": "\ud83d\udc02\u813e\u6c23"}, "content": "\u6a02\u5929\u5973\u5b69\u751f\u6d3b\u4e00\u5b9a\u5f88\u7121\u6182\u7121\u616e\u5427\u2026\ud83d\ude02", "urls": [], "replies": {"first": [], "last": [], "noMoreReplies": true}, "images": [], "id": 23136326}]}
