{"noMoreComments": true, "cursorEnd": 0, "id": "2169945", "comments": [{"postBy": {"location": "\u9ad8\u96c4\u5e02\u00b7\u53f0\u7063", "utc": 1442900839000, "level": 0, "avatar": "http://filestoresg1.beetalkmobile.com:8081/file/2210037064650858131", "name": "\u5ba5\u5ba5"}, "content": "\u55e8\u4f60\u597d\u5e25 \u4f60\u597d\u50cfTina", "urls": [], "replies": {"first": [{"content": "\u55e8 \u4f60\u597d\u6b63", "reply": "", "id": 13162498, "name": "Chael Mi"}], "last": [], "noMoreReplies": true}, "images": [], "id": 20804521}]}
