{"noMoreComments": true, "cursorEnd": 0, "id": "2119922", "comments": [{"postBy": {"location": "\u6843\u5712\u5e02\u00b7\u53f0\u7063", "utc": 1442234210000, "level": 0, "avatar": "http://filestoresg1.beetalkmobile.com:8081/file/1334548734654366912", "name": "\u2660\u4ea6\u51e1\u2660"}, "content": "\u8aaa\u7684\u51fa\u54f2\u7406\u672a\u5fc5\u505a\u7684\u5230\u554a\uff08\u5606<br /><br />\u256e(\u256f\u25bd\u2570)\u256d", "urls": [], "replies": {"first": [{"content": "\u904e\u9663\u5b50\u5c31\u53ef\u4ee5\u4e86\uff01", "reply": "", "id": 12823607, "name": "\u66fe\u53ef\u611b-\u4f86\u804a\u5929"}, {"content": "\u54c8\uff5e~\n\n\u667a\u6167\u5316\u70ba\u9818\u609f\u4e0d\u662f\u9019\u9ebc\u5bb9\u6613\u7684", "reply": "\u66fe\u53ef\u611b-\u4f86\u804a\u5929", "id": 12823692, "name": "\u2660\u4ea6\u51e1\u2660"}], "last": [], "noMoreReplies": true}, "images": [], "id": 20257435}, {"postBy": {"location": "\u65b0\u5317\u5e02\u00b7\u53f0\u7063", "utc": 1442237317000, "level": 0, "avatar": "http://filestoresg1.beetalkmobile.com:8081/file/-69369274665447626", "name": "\u83ab\u540d"}, "content": "\u4e00\u500b\u4eba\u7684\u6210\u5c31\u4e0d\u5728\u65bc\u8cfa\u591a\u5c11\u9322\uff0c<br />\u800c\u662f\u5e6b\u52a9\u5225\u4eba\u4ec0\u9ebc\u4e8b\uff0c<br />\u591a\u5c11\u4eba\u611f\u8b1d\u4ed6<br /><br />\u8cfa\u518d\u591a\u9322\uff0c<br />\u9032\u68fa\u6750\u4e5f\u5e36\u4e0d\u8d70<br /><br />\u4f46\u662f\u5e6b\u52a9\u4e86\u5225\u4eba\uff0c<br />\u6703\u8b93\u5225\u4eba\u61f7\u5ff5\u4ed6<br /><br />\u5982\u679c\u6211\u5011\u6c92\u90a3\u9ebc\u5049\u5927\uff0c<br />\u90a3\u5c31\u8acb\u81f3\u5c11\u5584\u5f85\u8eab\u908a\u7684\u89aa\u4eba\u670b\u53cb\uff0c<br />\u8b93\u4ed6\u5011\u904e\u7684\u958b\u5fc3\uff0c<br />\u6bcf\u4eba\u53ea\u8981\u4e00\u4e9b\u5c0f\u8209\u52d5\uff0c<br />\u90fd\u53ef\u4ee5\u8b93\u8eab\u908a\u7684\u89aa\u4eba\u670b\u53cb\u5011\u904e\u7684\u66f4\u597d\uff0c<br />\u5e73\u51e1\u3001\u5feb\u6a02\u3001\u77e5\u8db3\u5c31\u662f\u4e00\u7a2e\u5e78\u798f", "urls": [], "replies": {"first": [], "last": [], "noMoreReplies": true}, "images": [], "id": 20261199}, {"postBy": {"location": "\u65b0\u5317\u5e02\u00b7\u53f0\u7063", "utc": 1442238548000, "level": 0, "avatar": "http://filestoresg1.beetalkmobile.com:8081/file/-7218677552474819476", "name": "\u6046"}, "content": "\u8b1d\u8b1d\u59b3\u7684\u4e3b\u984c\uff0c\u6211\u53d7\u6559\u4e86\u3002", "urls": [], "replies": {"first": [{"content": "\u5475\uff0c\u6211\u4e5f\u662f\u6709\u6240\u9ad4\u609f", "reply": "", "id": 12827117, "name": "\u66fe\u53ef\u611b-\u4f86\u804a\u5929"}], "last": [], "noMoreReplies": true}, "images": [], "id": 20262782}, {"postBy": {"location": "\u82b1\u84ee\u7e23\u00b7\u53f0\u7063", "utc": 1442238786000, "level": 0, "avatar": "http://filestoresg1.beetalkmobile.com:8081/file/-254861294360704726", "name": "\u6bba\u99ac\u7279"}, "content": "\u8001\u8872\u53d7\u6559\u4e86\uff0c\u5c0d\u4e86\u9019\u662f\u8b1b\u7d66\u7aae\u4eba\u807d\u7684\u3002", "urls": [], "replies": {"first": [], "last": [], "noMoreReplies": true}, "images": [], "id": 20263065}, {"postBy": {"location": "\u53f0\u4e2d\u5e02\u00b7\u53f0\u7063", "utc": 1442244027000, "level": 0, "avatar": "http://filestoresg1.beetalkmobile.com:8081/file/-2793927206912568409", "name": "\u54c7\u52d2"}, "content": "\u8aaa\u4e86\u597d\u963f\uff0c\u4e0d\u932f", "urls": [], "replies": {"first": [], "last": [], "noMoreReplies": true}, "images": [], "id": 20270140}, {"postBy": {"location": "\u65b0\u5317\u5e02\u00b7\u53f0\u7063", "utc": 1442244220000, "level": 0, "avatar": "http://filestoresg1.beetalkmobile.com:8081/file/-4910524468807906044", "name": "\u8ac7\u5929\u8aaa\u5730"}, "content": "\u65bd\u6bd4\u53d7\u66f4\u6709\u798f", "urls": [], "replies": {"first": [], "last": [], "noMoreReplies": true}, "images": [], "id": 20270411}, {"postBy": {"location": "\u5609\u7fa9\u5e02\u00b7\u53f0\u7063", "utc": 1442245866000, "level": 0, "avatar": "http://filestoresg1.beetalkmobile.com:8081/file/-5439340089589116221", "name": "\u912d\u502b\u4ed4"}, "content": "\u59b3\u77e5\u9053\u723d\u5b57\u600e\u9ebc\u5beb\u55ce\uff01\uff08\u4e00\u500b\u4eba\u63d2\u56db\u500b\uff0c\u6216\u8005\u4e00\u500b\u4eba\u6709\u56db\u500b\u63d2\uff09\u6709\u4e00\u6a23\u55ce\uff1f\u2026\u2026\u60f3\u6cd5\u53ef\u4ee5\u8b8a\u7684\uff01\u7d50\u679c\u5c31\u4e0d\u4e00\u6a23\u4e86\uff01", "urls": [], "replies": {"first": [], "last": [], "noMoreReplies": true}, "images": [], "id": 20272602}]}
