{"noMoreComments": true, "cursorEnd": 0, "id": "2280987", "comments": [{"postBy": {"location": "\u53f0\u4e2d\u5e02\u00b7\u53f0\u7063", "utc": 1444351974000, "level": 0, "avatar": "http://filestoresg1.beetalkmobile.com:8081/file/3112667943066400514", "name": "\u671f\u5f85"}, "content": "\u6709\u7b2c\u4e8c\u5f35\u6709\u9ede\u50cf\u91d1\u5b87\u5f6c", "urls": [], "replies": {"first": [{"content": "\u4ed6\u662f\u8ab0@@", "reply": "", "id": 13966472, "name": "\u55b3\u55b3"}, {"content": "\u97d3\u570b\u5f88\u7d05\u7684\u660e\u661f", "reply": "", "id": 14015005, "name": "\u671f\u5f85"}], "last": [], "noMoreReplies": true}, "images": [], "id": 22068010}, {"postBy": {"location": "\u96f2\u6797\u7e23\u00b7\u53f0\u7063", "utc": 1444357450000, "level": 0, "avatar": "http://filestoresg1.beetalkmobile.com:8081/file/3682128110847178768", "name": "\u5f90\u592a\u745c"}, "content": "\u6a13\u4e0a+1 \u6211\u5c31\u89ba\u5f97\u6709\u50cf\u8ab0", "urls": [], "replies": {"first": [{"content": "\u6709\u9019\u7a2e\u4e8b\uff01\uff01\uff01", "reply": "", "id": 13966502, "name": "\u55b3\u55b3"}], "last": [], "noMoreReplies": true}, "images": [], "id": 22073294}, {"postBy": {"location": "\u9ad8\u96c4\u5e02\u00b7\u53f0\u7063", "utc": 1444360753000, "level": 0, "avatar": "http://filestoresg1.beetalkmobile.com:8081/file/8263618242757257214", "name": "\ud83d\ude2a\ud83d\ude2a"}, "content": "\u8d85\u6709\u884c\u60c5\u5427 \u5f88\u5e25\u8036", "urls": [], "replies": {"first": [{"content": "\u8b1d\u8b1d\u554a\uff5e\u53ef\u60dc\u5c31\u662f\u6c92\u4eba\u8981...", "reply": "", "id": 13967879, "name": "\u55b3\u55b3"}], "last": [{"content": "\u771f\u7684\u4e0d\u53ef\u80fd", "reply": "", "id": 13975772, "name": "\u55b3\u55b3"}, {"content": "\u7537\u751f\u8981\u4e3b\u52d5\u4e00\u9ede\u54a9", "reply": "\u55b3\u55b3", "id": 13982394, "name": "\ud83d\ude2a\ud83d\ude2a"}], "noMoreReplies": false}, "images": [], "id": 22076722}, {"postBy": {"location": "\u9ad8\u96c4\u5e02\u00b7\u53f0\u7063", "utc": 1444361057000, "level": 0, "avatar": "http://filestoresg1.beetalkmobile.com:8081/file/-763972550704089547", "name": "\u5c0f\u7440"}, "content": "\ud83d\udc4d", "urls": [], "replies": {"first": [], "last": [], "noMoreReplies": true}, "images": [], "id": 22077055}, {"postBy": {"location": "", "utc": 1444414081000, "level": 0, "avatar": "http://filestoresg1.beetalkmobile.com:8081/file/1", "name": "\u8d85\u7d1a\u58de\u5973\u4eba"}, "content": "\u5e25\u5e25\u7684", "urls": [], "replies": {"first": [{"content": "\u8b1d\u8b1d\u5594^^", "reply": "", "id": 14026632, "name": "\u55b3\u55b3"}], "last": [], "noMoreReplies": true}, "images": [], "id": 22142464}, {"postBy": {"location": "\u53f0\u4e2d\u5e02\u00b7\u53f0\u7063", "utc": 1444418562000, "level": 0, "avatar": "http://filestoresg1.beetalkmobile.com:8081/file/-7092784581047557433", "name": "\u8336\u8c93\u5152"}, "content": "\u6c92\u6709", "urls": [], "replies": {"first": [{"content": "\u6211\u4e5f\u9019\u9ebc\u8a8d\u70ba\uff5e", "reply": "", "id": 14026649, "name": "\u55b3\u55b3"}], "last": [{"content": "\u7576\u7136^_^", "reply": "", "id": 14098599, "name": "\u55b3\u55b3"}, {"content": "\u54c8\u54c8\u54c8", "reply": "\u55b3\u55b3", "id": 14098914, "name": "\u8336\u8c93\u5152"}], "noMoreReplies": false}, "images": [], "id": 22145100}, {"postBy": {"location": "\u53f0\u5357\u5e02\u00b7\u53f0\u7063", "utc": 1444420583000, "level": 0, "avatar": "http://filestoresg1.beetalkmobile.com:8081/file/6881318812048397072", "name": "\u860b\u860b\u679c"}, "content": "\u771f\u7684\u6709\u50cf\u91d1\u5b87\u5f6c\u8036", "urls": [], "replies": {"first": [{"content": "\u9019\u662f\u597d\u4e8b\u55ce\uff5e", "reply": "", "id": 14026657, "name": "\u55b3\u55b3"}, {"content": "\u7576\u7136\u662f\u597d\u4e8b", "reply": "", "id": 14034642, "name": "\u860b\u860b\u679c"}], "last": [], "noMoreReplies": true}, "images": [], "id": 22145886}, {"postBy": {"location": "\u5f70\u5316\u7e23\u00b7\u53f0\u7063", "utc": 1444682828000, "level": 0, "avatar": "http://filestoresg1.beetalkmobile.com:8081/file/-2750981388472153654", "name": "\u6c92\u4eba\u5728\u5bb6"}, "content": "\u6709\uff01\u4f60\u53ef\u4ee5\u9080\u4f60\u670b\u53cb\u4e00\u8d77\u4f86\u653e", "urls": [], "replies": {"first": [{"content": "\u4f60\u4eba\u771f\u597d", "reply": "", "id": 14178548, "name": "\u55b3\u55b3"}], "last": [], "noMoreReplies": true}, "images": [], "id": 22394974}, {"postBy": {"location": "\u5609\u7fa9\u7e23\u00b7\u53f0\u7063", "utc": 1444688191000, "level": 0, "avatar": "http://filestoresg1.beetalkmobile.com:8081/file/-5815689720226419968", "name": "\u73a7\u7483"}, "content": "\u6211\u600e\u9ebc\u770b\u6210\u6556\u72ac......", "urls": [], "replies": {"first": [{"content": "\u54ea\u88e1\u50cf", "reply": "", "id": 14178563, "name": "\u55b3\u55b3"}, {"content": "\u7b2c\u4e8c\u5f35\u770b\u5230\u7b2c\u4e00\u773c\u883b\u50cf\u7684", "reply": "", "id": 14201502, "name": "\u73a7\u7483"}], "last": [], "noMoreReplies": true}, "images": [], "id": 22396430}, {"postBy": {"location": "\u82b1\u84ee\u7e23\u00b7\u53f0\u7063", "utc": 1444714661000, "level": 0, "avatar": "http://filestoresg1.beetalkmobile.com:8081/file/-8133293113027681329", "name": "\ud83d\udc84\ud83d\udc84\ud83d\udc84\ud83d\udc84"}, "content": "\u4f60\u7684\u53f3\u624b\u597d\u4e00\u9ede\u6c92\uff1f", "urls": [], "replies": {"first": [{"content": "\u597d\u591a\u4e86\uff0c\u8b1d\u8b1d\u95dc\u5fc3^_^\uff08\u5176\u5be6\u9019\u662f\u5de6\u624b", "reply": "", "id": 14191696, "name": "\u55b3\u55b3"}, {"content": "\u55ef\u55ef\uff0c\u90a3\u5c31\u597d\n\uff3e\uff3eb", "reply": "", "id": 14202777, "name": "\ud83d\udc84\ud83d\udc84\ud83d\udc84\ud83d\udc84"}], "last": [], "noMoreReplies": true}, "images": [], "id": 22419383}, {"postBy": {"location": "\u6843\u5712\u5e02\u00b7\u53f0\u7063", "utc": 1444716257000, "level": 0, "avatar": "http://filestoresg1.beetalkmobile.com:8081/file/-1002884334149506549", "name": "\u55b3\u55b3"}, "content": "\u597d\u591a\u4e86^_^", "urls": [], "replies": {"first": [], "last": [], "noMoreReplies": true}, "images": ["http://filestoresg1.beetalkmobile.com:8081/file/8baf0745a82ad825099fd96792d4ad8c"], "id": 22421114}]}
