{"noMoreComments": true, "cursorEnd": 0, "id": "2240221", "comments": [{"postBy": {"location": "Taichung City\u00b7Taiwan", "utc": 1443845053000, "level": 0, "avatar": "http://filestoresg1.beetalkmobile.com:8081/file/4820118240622006379", "name": "lin"}, "content": "\u9577\u9838\u9e7f\u5403\u6a39\u8449\uff0c\u559d\u6c34\uff0c\u4e0d\u559d\u5496\u5561\u2026\u2026", "urls": [], "replies": {"first": [{"content": "\u8aaa\u4e0d\u5b9a\u7260\u4e00\u76f4\u5f88\u60f3\u559d", "reply": "", "id": 13693473, "name": "\u2606\u715e\u6c23\u6b38\u2197\u7403\u5f97\u61e6"}], "last": [], "noMoreReplies": true}, "images": [], "id": 21601831}]}
