{"noMoreComments": true, "cursorEnd": 0, "id": "2981254", "comments": [{"postBy": {"location": "\u53f0\u4e2d\u5e02\u00b7\u53f0\u7063", "utc": 1453780208000, "level": 0, "avatar": "http://filestoresg1.beetalkmobile.com:8081/file/1833850164907361433", "name": "\ud83d\udc96Mie\ud83d\udc8b"}, "content": "\u53ef\u4ee5\u642c\u4eba\u55ce\uff01\uff1f", "urls": [], "replies": {"first": [{"content": "\u53ef\u4ee5\u554a", "reply": "", "id": 19307702, "name": "\u5229\u9054\u514b"}], "last": [{"content": "\u8981\u6536\u8cbb", "reply": "\ud83d\udc96Mie\ud83d\udc8b", "id": 19308808, "name": "\u5229\u9054\u514b"}, {"content": "\u5df2\u8b80\u8036", "reply": "\ud83d\udc96Mie\ud83d\udc8b", "id": 19745041, "name": "\u5229\u9054\u514b"}], "noMoreReplies": false}, "images": [], "id": 30151010}]}
