{"noMoreComments": true, "cursorEnd": 0, "id": "2920857", "comments": [{"postBy": {"location": "\u6843\u5712\u5e02\u00b7\u53f0\u7063", "utc": 1456650015000, "level": 0, "avatar": "http://filestoresg1.beetalkmobile.com:8081/file/-6167221192010364391", "name": "\u7d0d\u5e1d\u9b6f\u65af"}, "content": "\u51cc\u6668\u96e8\u597d\u807d \u314b\u314b", "urls": [], "replies": {"first": [{"content": "\u771f\u7684\u597d\u807d", "reply": "", "id": 21030094, "name": "\u598d"}], "last": [], "noMoreReplies": true}, "images": [], "id": 32737183}, {"postBy": {"location": "\u53f0\u4e2d\u5e02\u00b7\u53f0\u7063", "utc": 1456936184000, "level": 0, "avatar": "http://filestoresg1.beetalkmobile.com:8081/file/5516018939998692173", "name": "\ubc29\uc544_\u82b3\u5152_\ucd08\ub9e4\ud83c\udf53"}, "content": "\u559c\u6b61\u6b4c\uff5e\uff5e\uff5e\u4eba\u53c8\u8d85\u53ef\u611b\uff01", "urls": [], "replies": {"first": [{"content": "\u8d85\u53ef\u611b\u7684", "reply": "", "id": 21208005, "name": "\u598d"}], "last": [], "noMoreReplies": true}, "images": [], "id": 33000172}]}
