{"noMoreComments": false, "cursorEnd": 23, "id": "2948454", "comments": [{"postBy": {"location": "\u96f2\u6797\u7e23\u00b7\u53f0\u7063", "utc": 1453332154000, "level": 0, "avatar": "http://filestoresg1.beetalkmobile.com:8081/file/5098548668976495593", "name": "Jun"}, "content": "\u7345\u5b50\u5c31\u662f\u611b\u9738\u9053", "urls": [], "replies": {"first": [{"content": "\u5c31\u662f\u4efb\u6027", "reply": "", "id": 19027504, "name": "158\ud83e\udd81\ufe0f"}, {"content": "\u7345\u5b50\u738b", "reply": "", "id": 19067064, "name": "Jun"}], "last": [], "noMoreReplies": true}, "images": [], "id": 29741957}, {"postBy": {"location": "\u6843\u5712\u5e02\u00b7\u53f0\u7063", "utc": 1453386067000, "level": 0, "avatar": "http://filestoresg1.beetalkmobile.com:8081/file/-428181706166249201", "name": "\u5c0f\u590f"}, "content": "\u4e0d\u7ba1\u8ab0\u932f\u90fd\u8981\u5148\u4f4e\u982d\u8aaa\u62b1\u6b49<br />\u7345\u5b50\u5ea7\u6211\u90fd\u77e5\u9053", "urls": [], "replies": {"first": [{"content": "\u4f60\u5404\u7a2e\u4e86\u89e3\u600e\u9ebc\u9084\u5728\u9019\u88e1\uff1f\n\u4e0d\u5feb\u53bb\u958b\u9928\u6536\u8cbb\u55ce\uff1f", "reply": "", "id": 19073895, "name": "SickBoy"}], "last": [], "noMoreReplies": true}, "images": [], "id": 29795779}, {"postBy": {"location": "", "utc": 1453393389000, "level": 0, "avatar": "http://filestoresg1.beetalkmobile.com:8081/file/1333289804742823004", "name": "SickBoy"}, "content": "\u4e00\u7bc7\u6587\u7ae0\u5168\u90fd\u662f\u8907\u88fd\u4f86\u7684\uff0c<br />\u59b3\u4e00\u5b9a\u5fd8\u4e86\u5beb\u5230\u7279\u5fb5\u3010\u5404\u7a2e\u61f6\u60f0\u3011", "urls": [], "replies": {"first": [{"content": "\u6a19\u9ede\u7b26\u865f\u8001\u5a18\u52a0\u4e0a\u7684\u3002", "reply": "", "id": 19074617, "name": "158\ud83e\udd81\ufe0f"}], "last": [{"content": "\u9762\u5c0d\u9ec3\u5b89 \u8f9b\u82e6\u4f60\u4e86", "reply": "\u541b\u7f8a", "id": 19311356, "name": "158\ud83e\udd81\ufe0f"}, {"content": "\u52a0\u85e4\u9df9\u90fd\u77e5\u9053\u51fa\u8655\u8981\u9644\u660e\uff0c\u539f\u4f86\u59b3\u4e0d\u77e5\u9053\u5594\u3002\n\u4e0d\u77e5\u9053\u5c31\u7576\u5225\u4eba\u662f\u9ec3\u5b89\uff0c\u59b3\u662f\u653f\u5ba2\u5594", "reply": "158\ud83e\udd81\ufe0f", "id": 19320550, "name": "SickBoy"}], "noMoreReplies": false}, "images": ["http://filestoresg1.beetalkmobile.com:8081/file/9d8593dc0a307b665528e3309eaebd3e", "http://filestoresg1.beetalkmobile.com:8081/file/be81f6f3d3706ff108ba170b642674c5", "http://filestoresg1.beetalkmobile.com:8081/file/3222ac1735b3d63301de44038511504d"], "id": 29806765}, {"postBy": {"location": "", "utc": 1453393624000, "level": 0, "avatar": "http://filestoresg1.beetalkmobile.com:8081/file/4313230190744764766", "name": "too (4.0)\u9ad8\u6e05\u7248"}, "content": "   ", "urls": [], "replies": {"first": [], "last": [], "noMoreReplies": true}, "images": ["http://filestoresg1.beetalkmobile.com:8081/file/faeb179cdfe77f96c1f77018d557acdc"], "id": 29807077}, {"postBy": {"location": "\u9999\u6e2f", "utc": 1453406624000, "level": 0, "avatar": "http://filestoresg1.beetalkmobile.com:8081/file/-1873087311010434052", "name": "\u6fc0"}, "content": "\u6709\u9738\u6c23", "urls": [], "replies": {"first": [], "last": [], "noMoreReplies": true}, "images": [], "id": 29817014}, {"postBy": {"location": "\u6843\u5712\u5e02\u00b7\u53f0\u7063", "utc": 1453418859000, "level": 0, "avatar": "http://filestoresg1.beetalkmobile.com:8081/file/-3119204529095273984", "name": "\u6ed1\u7a3d\u7684\u54e1\u5916"}, "content": "\u53ea\u6703\u8eb2\u8d77\u4f86\u9ed8\u9ed8\u7684\u8214\u8457\u81ea\u5df1\u7684\u50b7\u75a4....", "urls": [], "replies": {"first": [], "last": [], "noMoreReplies": true}, "images": [], "id": 29820917}, {"postBy": {"location": "\u65b0\u5317\u5e02\u00b7\u53f0\u7063", "utc": 1453429349000, "level": 0, "avatar": "http://filestoresg1.beetalkmobile.com:8081/file/3632292751433429530", "name": "Nini"}, "content": "\u6703\u6539\u4e00\u5b9a\u662f\u611b\u5230\u4e86<br />\u7576\u4e0b\u8b8a\u55b5\u55b5<br />\u7b49\u5230\u96e2\u958b\u5f8c\u53c8\u662f\u4e00\u982d\u7345\u5b50<br />\u8c93\u79d1\u8840\u7d71", "urls": [], "replies": {"first": [{"content": "\u7121\u8aa4\ud83d\ude2d\ud83d\ude2d", "reply": "", "id": 19311368, "name": "158\ud83e\udd81\ufe0f"}], "last": [{"content": "\u8a8d\u540c\u6211\u5c31\u662f\u9019\u6a23", "reply": "", "id": 19571429, "name": "\u5bcc\u6d32"}, {"content": "\u4f60\u4e5f\u7345\u5b50\uff0c\u96e3\u602a\u6703\u5beb~\u60f3\u8981\u771f\u611b\u771f\u7684\u597d\u96e3", "reply": "", "id": 19579329, "name": "Nini"}], "noMoreReplies": true}, "images": [], "id": 29828282}, {"postBy": {"location": "\u9ad8\u96c4\u5e02\u00b7\u53f0\u7063", "utc": 1453492063000, "level": 0, "avatar": "http://filestoresg1.beetalkmobile.com:8081/file/5006910973750107697", "name": "Xuan"}, "content": "\u6d3b\u51fa\u771f\u6b63\u7684\u81ea\u5df1\u9019\u624d\u662f\u7345\u5b50\u5ea7\u7684\u512a\u9ede\u963f<br />: \" )  \u4e0d\u96a8\u6ce2\u9010\u6d41\u624d\u662f\u539f\u4f86\u7684\u59b3", "urls": [], "replies": {"first": [], "last": [], "noMoreReplies": true}, "images": [], "id": 29897014}, {"postBy": {"location": "\u53f0\u5357\u5e02\u00b7\u53f0\u7063", "utc": 1453504344000, "level": 0, "avatar": "http://filestoresg1.beetalkmobile.com:8081/file/2", "name": "User blocked"}, "content": "\u6211\u4ee5\u8eab\u70ba\u7345\u5b50\u5ea7\u70ba\u69ae\ud83d\ude06\ud83d\ude06\ud83d\ude06", "urls": [], "replies": {"first": [], "last": [], "noMoreReplies": true}, "images": [], "id": 29900577}, {"postBy": {"location": "\u53f0\u5357\u5e02\u00b7\u53f0\u7063", "utc": 1453719177000, "level": 0, "avatar": "http://filestoresg1.beetalkmobile.com:8081/file/-5129148060412866500", "name": "\u5091\u514b\u771f\u7684\u592a"}, "content": "\u91cd\u9ede\u662f? \u5176\u4ed611\u661f\u5ea7\u5973\u90fd\u662f\u6b4c\u4ed4\u6232\u55ce? \u54c8", "urls": [], "replies": {"first": [], "last": [], "noMoreReplies": true}, "images": [], "id": 30098271}, {"postBy": {"location": "\u6843\u5712\u5e02\u00b7\u53f0\u7063", "utc": 1453723547000, "level": 0, "avatar": "http://filestoresg1.beetalkmobile.com:8081/file/8003201105121276713", "name": "\u5c0f\u68a8\uff08\u7b2c\u4e94\u4eba\u683c\uff09"}, "content": "\u9019\u7b49\u8eab\u7684\u5a03\u5a03\u6839\u672c\u662f\u70ba\u4e86\u59b3\u8cb7\u7684\u561b\uff0c\u54c8\u54c8", "urls": [], "replies": {"first": [], "last": [], "noMoreReplies": true}, "images": [], "id": 30103212}, {"postBy": {"location": "\u6843\u5712\u5e02\u00b7\u53f0\u7063", "utc": 1453728947000, "level": 0, "avatar": "http://filestoresg1.beetalkmobile.com:8081/file/-392513550312611840", "name": "Chris cai"}, "content": "\u9019\u6a23\u5f88\u597d", "urls": [], "replies": {"first": [], "last": [], "noMoreReplies": true}, "images": [], "id": 30110722}, {"postBy": {"location": "\u9ad8\u96c4\u5e02\u00b7\u53f0\u7063", "utc": 1453731793000, "level": 0, "avatar": "http://filestoresg1.beetalkmobile.com:8081/file/1822738506893057719", "name": "\u96f7\u5e1d\u5c2c\u5c2c"}, "content": "\u6211\u9084\u6c92\u4ea4\u904e\u7345\u5b50 \u60f3\u8a66\u8a66\u770b", "urls": [], "replies": {"first": [], "last": [], "noMoreReplies": true}, "images": [], "id": 30115243}, {"postBy": {"location": "\u65b0\u5317\u5e02\u00b7\u53f0\u7063", "utc": 1453736327000, "level": 0, "avatar": "http://filestoresg1.beetalkmobile.com:8081/file/4165414056004883441", "name": "\u4faf\u723a"}, "content": "\u7345\u5b50\u7684\u9738\u9053\u4e5f\u662f\u4e00\u7a2e\u95dc\u5fc3<br />\u53ef\u4ee5\u88ab\u7345\u5b50\u9738\u9053\u7684\u4e5f\u4e0d\u591a\u5594<br />", "urls": [], "replies": {"first": [{"content": "\u6c92\u932f\ud83d\ude24\ud83d\ude24", "reply": "", "id": 19311396, "name": "158\ud83e\udd81\ufe0f"}], "last": [], "noMoreReplies": true}, "images": [], "id": 30122448}, {"postBy": {"location": "\u6843\u5712\u5e02\u00b7\u53f0\u7063", "utc": 1453736391000, "level": 0, "avatar": "http://filestoresg1.beetalkmobile.com:8081/file/4164001181667787521", "name": "\ud83d\ude06\ud83d\ude06\ud83d\ude06"}, "content": "\u6211\u4e5f\u662f\u7345\u5b50\u5973\uff5e", "urls": [], "replies": {"first": [{"content": "\ud83e\udd18\ud83c\udffb\ud83e\udd18\ud83c\udffb\ud83e\udd18\ud83c\udffb\ud83e\udd18\ud83c\udffb", "reply": "", "id": 19311390, "name": "158\ud83e\udd81\ufe0f"}], "last": [], "noMoreReplies": true}, "images": [], "id": 30122526}, {"postBy": {"location": "\u65b0\u5317\u5e02\u00b7\u53f0\u7063", "utc": 1453739553000, "level": 0, "avatar": "http://filestoresg1.beetalkmobile.com:8081/file/5564585469719394997", "name": "\u9b0d\u9b1a\u5927\u53d4"}, "content": "\u9019\u7bc7\u6709\u9ede\u9762\u719f\u5152~\u4f46\u7121\u6240\u8b02<br />\u4e3b\u89d2\u662f\u6b63\u59b9\u5c31\u597d...<br />\u7345\u5b50\u5973\u611f\u89ba\u5f88\u611b\u73a9\u554a \u5728\u4eba\u7fa4\u4e2d\u5f88\u9192\u76ee", "urls": [], "replies": {"first": [{"content": "\u6211\u4e0d\u611b\u73a9\ud83e\udd18\ud83c\udffb", "reply": "", "id": 19311414, "name": "158\ud83e\udd81\ufe0f"}], "last": [], "noMoreReplies": true}, "images": [], "id": 30126640}, {"postBy": {"location": "\u6843\u5712\u5e02\u00b7\u53f0\u7063", "utc": 1453741698000, "level": 0, "avatar": "http://filestoresg1.beetalkmobile.com:8081/file/1474181225546344244", "name": "\u963f\u98a8"}, "content": "\u7345\u5b50\u7537\u5973\u90fd\u4e0d\u932f\uff0c\u81f3\u5c11\u4e0d\u505a\u4f5c\uff0c\u8b9a\uff0c\u6211\u5c31\u662f\u7345\u5b50\u7537\u3002", "urls": [], "replies": {"first": [], "last": [], "noMoreReplies": true}, "images": [], "id": 30128920}, {"postBy": {"location": "\u6843\u5712\u5e02\u00b7\u53f0\u7063", "utc": 1453742102000, "level": 0, "avatar": "http://filestoresg1.beetalkmobile.com:8081/file/-827503430799904476", "name": "\u2716\u5713\u4ed4\u2716"}, "content": "\u4ffa\u662f\u6eab\u67d4\u7345\u5b50\u7537\uff0c\uff0c\u7345\u5b50\u5c31\u662f\u68d2\ud83d\ude4c\ud83d\ude4c\ud83d\ude4c\u8def\u904e\u6309\u500b\u8b9a", "urls": [], "replies": {"first": [], "last": [], "noMoreReplies": true}, "images": [], "id": 30129336}, {"postBy": {"location": "\u53f0\u5317\u5e02\u00b7\u53f0\u7063", "utc": 1453748890000, "level": 0, "avatar": "http://filestoresg1.beetalkmobile.com:8081/file/6023435867084132719", "name": "\ud83c\udf70\u8c93\u4ed4\ud83d\udc31\ud83d\udc95"}, "content": "\u7345\u5b50\u5ea7\u771f\u6027\u60c5\u3001\u559c\u60e1\u5206\u660e<br />\u5c0d\u81ea\u5df1\u611b\u7684\u5bb6\u4eba\u670b\u53cb\u7537\u4eba\u5973\u4eba\u6839\u672c\u638f\u5fc3\u80ba<br />\u89ba\u5f97\u6b63\u9ede", "urls": [], "replies": {"first": [{"content": "\u4f46\u662f\u638f\u5fc3\u80ba\u7e3d\u662f\u88ab\u50b7", "reply": "", "id": 19311440, "name": "158\ud83e\udd81\ufe0f"}, {"content": "\u7e3d\u6709\u4e00\u5929\u6703\u9047\u5230\u61c2\u5f97\u56de\u5831\u7684\u4eba\uff1aP\n\u5148\u770b\u597d\u5c0d\u8c61\u5c31\u662f\u4e86\n\u5f80\u597d\u7684\u7b2c\u65b9\u60f3\u56c9", "reply": "", "id": 19343600, "name": "\ud83c\udf70\u8c93\u4ed4\ud83d\udc31\ud83d\udc95"}], "last": [], "noMoreReplies": true}, "images": [], "id": 30133698}]}
