{"noMoreComments": true, "cursorEnd": 0, "id": "2451409", "comments": [{"postBy": {"location": "\u82d7\u6817\u7e23\u00b7\u53f0\u7063", "utc": 1446501342000, "level": 0, "avatar": "http://filestoresg1.beetalkmobile.com:8081/file/-8443125598792393951", "name": "\u7b49\u5f85\u4e00\u500b\u4eba\u7684\u5496\u5561"}, "content": "\u56e0\u70ba\u611b\u7684\u771f \u611b\u7684\u6df1<br />\u624d\u6703\u8b93\u4eba\u7e7c\u7e8c\u50bb\u4e0b\u53bb<br />\u5c31\u7b97\u76fc\u5230\u4ed6\u56de\u4f86<br />\u4e5f\u56de\u4e0d\u53bb\u539f\u4f86\u7684\u611b<br />\u70ba\u4e86\u81ea\u5df1\u5b78\u6703\u81ea\u79c1\u4e00\u4e0b<br />\u8981\u611b\u5c31\u611b<br />\u4e0d\u8981\u518d\u662f\u6b98\u7834\u7684\u611b", "urls": [], "replies": {"first": [{"content": "\u6211\u807d\u4e86\u5f88\u591a\u4eba\u7684\u52f8\uff0c\u4e5f\u81ea\u5df1\u5fc3\u75bc\uff0c\u4f46\u600e\u9ebc\u80fd\u6709\u8aaa\u4e0d\u611b\u5c31\u4e0d\u611b\u7684\u81ea\u79c1", "reply": "", "id": 15265707, "name": "\u5c0f\u541b\u541b"}, {"content": "\u53ef\u662f\u7576\u5169\u500b\u4eba\u4e2d\u6709\u4e00\u4eba\u5df2\u7d93\u6c92\u611f\u89ba\n\u53c8\u8a72\u5982\u4f55\u5462\uff1f\n\u611b\u5df2\u7d93\u6c92\u4e86\u5fc3\u600e\u6703\u6210\u70ba\u611b\u5462\uff1f", "reply": "\u5c0f\u541b\u541b", "id": 15274531, "name": "\u7b49\u5f85\u4e00\u500b\u4eba\u7684\u5496\u5561"}], "last": [], "noMoreReplies": true}, "images": [], "id": 24073487}, {"postBy": {"location": "\u6843\u5712\u5e02\u00b7\u53f0\u7063", "utc": 1446545036000, "level": 0, "avatar": "http://filestoresg1.beetalkmobile.com:8081/file/-9109664941349110985", "name": "\u5f65"}, "content": "\u5df2\u7d93\u932f\u611b\u4e86\u5c31\u8b93\u4ed6\u904e\u53bb\u5427\uff5e<br />\u72d7\u6539\u4e0d\u4e86\u5403\u5c4e\u2026\u5f37\u633d\u4e5f\u7121\u7528\u6b66\u4e4b\u5730", "urls": [], "replies": {"first": [], "last": [], "noMoreReplies": true}, "images": [], "id": 24106920}, {"postBy": {"location": "\u65b0\u5317\u5e02\u00b7\u53f0\u7063", "utc": 1446632885000, "level": 0, "avatar": "http://filestoresg1.beetalkmobile.com:8081/file/3251404321874730244", "name": "\u5728\u5730\u4e0b\u505c\u8eca\u5834\u9047\u5230\u4e86\u5929\u83dc"}, "content": "\u721b\u4eba\u662f\u53ea\u8981\u4ed6\u559c\u6b61\u6709\u4ec0\u9ebc\u4e0d\u53ef\u4ee5\u7684\u60f3\u6cd5\uff0c\u73fe\u5728\u9019\u7a2e\u7537\u5973\u5f88\u591a\uff0c\u53d7\u50b7\u7684\u6c38\u9060\u662f\u8a8d\u771f\u7684", "urls": [], "replies": {"first": [{"content": "\u670b\u53cb\u8aaa\uff0c\u56e0\u70ba\u6211\u7e3d\u662f\u6703\u539f\u8ad2\u4ed6\uff0c\u4f46\u6211\u771f\u7684\u6575\u4e0d\u904e\u60f3\u5ff5", "reply": "", "id": 15336101, "name": "\u5c0f\u541b\u541b"}], "last": [{"content": "\u6240\u4ee5\u8aaa\u8a8d\u771f\u611b\u7684\u90a3\u65b9\u5f88\u75db\u82e6\uff0c\u4e0d\u61c2\u7684\u6c38\u9060\u4e0d\u61c2", "reply": "\u5c0f\u541b\u541b", "id": 15338190, "name": "\u5728\u5730\u4e0b\u505c\u8eca\u5834\u9047\u5230\u4e86\u5929\u83dc"}, {"content": "\u771f\u7684\uff0c\u88ab\u6b3a\u8ca0\u4e86\uff0c\u9084\u662f\u50bb\u50bb\u611b\uff0c\u9084\u662f\u5e0c\u671b\u4ed6\u56de\u4f86", "reply": "\u5728\u5730\u4e0b\u505c\u8eca\u5834\u9047\u5230\u4e86\u5929\u83dc", "id": 15339153, "name": "\u5c0f\u541b\u541b"}], "noMoreReplies": true}, "images": [], "id": 24178596}]}
