{"noMoreComments": true, "cursorEnd": 0, "id": "2414046", "comments": [{"postBy": {"location": "\u9ad8\u96c4\u5e02\u00b7\u53f0\u7063", "utc": 1446005983000, "level": 0, "avatar": "http://filestoresg1.beetalkmobile.com:8081/file/109150719255905136", "name": "\u963f\u4e0d\u5566~yo"}, "content": "\u7ba1\u7ba1\u597d\u53b2\u5bb3", "urls": [], "replies": {"first": [], "last": [], "noMoreReplies": true}, "images": ["http://filestoresg1.beetalkmobile.com:8081/file/3843f4e75aea9efe2bc52b8503480221"], "id": 23654468}, {"postBy": {"location": "\u53f0\u6771\u7e23\u00b7\u53f0\u7063", "utc": 1446006325000, "level": 0, "avatar": "http://filestoresg1.beetalkmobile.com:8081/file/8525546093141872900", "name": "Stop\ud83d\udeb7"}, "content": "\u51fa\u5718\u771f\u7684\u662f\u5834\u5834\u6b61\u6a02\u55e8\u7ffb\u5929\u55b2\uff5e", "urls": [], "replies": {"first": [], "last": [], "noMoreReplies": true}, "images": [], "id": 23654808}]}
