{"noMoreComments": true, "cursorEnd": 0, "id": "2764974", "comments": [{"postBy": {"location": "\u53f0\u5317\u5e02\u00b7\u53f0\u7063", "utc": 1450786350000, "level": 0, "avatar": "http://filestoresg1.beetalkmobile.com:8081/file/6886057718746721623", "name": "Smile"}, "content": "\u5c31\u8aaa\u5427\uff01\u4f60\u7684\u624b\u634f\uff5e\u5f97\u5fc3\u61c9\u624b\u4e86\u5462\uff01", "urls": [], "replies": {"first": [{"content": "\u662f\u539a\uff01\u52c9\u5f37\u9084\u884c\u56c9\uff01^ ^", "reply": "", "id": 17681513, "name": "\u8001\u738b\u5b50"}], "last": [], "noMoreReplies": true}, "images": [], "id": 27617866}, {"postBy": {"location": "", "utc": 1450801837000, "level": 0, "avatar": "http://filestoresg1.beetalkmobile.com:8081/file/7259489253093076234", "name": "\u963f\u5370"}, "content": "\u559c\u6b61\u9019\u611f\u89ba~<br />\u6211\u662f\u770b\u5230\u7f85\u5fd7\u7965\u5728\u7bc0\u76ee\u88e1\u62ff\u6703\u7b11\u7684elmo\uff0c\u7136\u5f8c\u5c31\u8b8a\u6210\u6211\u7684\u56de\u61b6\u3002", "urls": [], "replies": {"first": [{"content": "\u5475\u5475\u5475\uff01\u611f\u8b1d\u59b3\u559c\u6b61\u56c9\uff01^ ^", "reply": "", "id": 17681500, "name": "\u8001\u738b\u5b50"}], "last": [], "noMoreReplies": true}, "images": [], "id": 27638851}]}
