{"noMoreComments": true, "cursorEnd": 0, "id": "2733610", "comments": [{"postBy": {"location": "\u82b1\u84ee\u7e23\u00b7\u53f0\u7063", "utc": 1450340558000, "level": 0, "avatar": "http://filestoresg1.beetalkmobile.com:8081/file/-2087154543218541001", "name": "Qnew Lee"}, "content": "1.2.4.6\u597d\u770b", "urls": [], "replies": {"first": [], "last": [], "noMoreReplies": true}, "images": [], "id": 27247618}, {"postBy": {"location": "\u65b0\u5317\u5e02\u00b7\u53f0\u7063", "utc": 1450340819000, "level": 0, "avatar": "http://filestoresg1.beetalkmobile.com:8081/file/3838817305994340529", "name": "\u60f3\u60f3\u5bf6\u8c9d"}, "content": "\u55ef\u2026\u90fd\u597d\u770b", "urls": [], "replies": {"first": [], "last": [], "noMoreReplies": true}, "images": [], "id": 27247840}, {"postBy": {"location": "\u65b0\u5317\u5e02\u00b7\u53f0\u7063", "utc": 1450340924000, "level": 0, "avatar": "http://filestoresg1.beetalkmobile.com:8081/file/1", "name": "\u8d85\u60e1\u7537\u5b50"}, "content": "\u4e0d\u7a7f\u6700\u597d\u770b", "urls": [], "replies": {"first": [], "last": [], "noMoreReplies": true}, "images": [], "id": 27247939}, {"postBy": {"location": "\u5609\u7fa9\u5e02\u00b7\u53f0\u7063", "utc": 1450341167000, "level": 0, "avatar": "http://filestoresg1.beetalkmobile.com:8081/file/6333181479600127296", "name": "Yao zong ."}, "content": "\u5f88\u591a\u65c5\u62cd\u90fd\u6c92\u7a7f\u8036\ud83d\ude02\ud83d\ude02", "urls": [], "replies": {"first": [], "last": [], "noMoreReplies": true}, "images": [], "id": 27248171}, {"postBy": {"location": "\u65b0\u5317\u5e02\u00b7\u53f0\u7063", "utc": 1450341829000, "level": 0, "avatar": "http://filestoresg1.beetalkmobile.com:8081/file/-322702262628697580", "name": "\u838a\u60df\u4e2d"}, "content": "\u7b2c3", "urls": [], "replies": {"first": [], "last": [], "noMoreReplies": true}, "images": [], "id": 27248724}, {"postBy": {"location": "\u82d7\u6817\u7e23\u00b7\u53f0\u7063", "utc": 1450350200000, "level": 0, "avatar": "http://filestoresg1.beetalkmobile.com:8081/file/2403720434806685696", "name": "\u4ec1"}, "content": "\u90fd\u4e0d\u932f", "urls": [], "replies": {"first": [], "last": [], "noMoreReplies": true}, "images": [], "id": 27255935}, {"postBy": {"location": "\u53f0\u5317\u5e02\u00b7\u53f0\u7063", "utc": 1450351431000, "level": 0, "avatar": "http://filestoresg1.beetalkmobile.com:8081/file/638413836057881351", "name": "Roman"}, "content": "\u7b2c\u4e94\u5f35\u6c7d\u8eca\u65c5\u9928\u62cd\u7167", "urls": [], "replies": {"first": [], "last": [], "noMoreReplies": true}, "images": [], "id": 27257067}, {"postBy": {"location": "\u53f0\u4e2d\u5e02\u00b7\u53f0\u7063", "utc": 1450351649000, "level": 0, "avatar": "http://filestoresg1.beetalkmobile.com:8081/file/-2966585714709508579", "name": "Rui Rui"}, "content": "\u7b2c\u4e8c\u5957", "urls": [], "replies": {"first": [], "last": [], "noMoreReplies": true}, "images": [], "id": 27257259}, {"postBy": {"location": "\u9ad8\u96c4\u5e02\u00b7\u53f0\u7063", "utc": 1450352581000, "level": 0, "avatar": "http://filestoresg1.beetalkmobile.com:8081/file/2120997516003775873", "name": "\u7d04\u675f\u4e0d\u9650\u5236"}, "content": "1,3,4", "urls": [], "replies": {"first": [], "last": [], "noMoreReplies": true}, "images": [], "id": 27258198}, {"postBy": {"location": "\u53f0\u4e2d\u5e02\u00b7\u53f0\u7063", "utc": 1450352812000, "level": 0, "avatar": "http://filestoresg1.beetalkmobile.com:8081/file/8558064160987688448", "name": "\u8cf4\u5c0f\u8ce2"}, "content": "\u90fd\u4e0d\u932f", "urls": [], "replies": {"first": [], "last": [], "noMoreReplies": true}, "images": [], "id": 27258431}, {"postBy": {"location": "\u6843\u5712\u5e02\u00b7\u53f0\u7063", "utc": 1450354330000, "level": 0, "avatar": "http://filestoresg1.beetalkmobile.com:8081/file/1584292905801624340", "name": "P0RSCHE"}, "content": "\u90fd\u4e0d\u559c\u6b61\uff0c\u56e0\u70ba\u611f\u89ba\u90a3\u896a\u5b50\u662f\u591a\u7684\u3002", "urls": [], "replies": {"first": [], "last": [], "noMoreReplies": true}, "images": [], "id": 27259984}, {"postBy": {"location": "\u65b0\u7af9\u7e23\u00b7\u53f0\u7063", "utc": 1450354497000, "level": 0, "avatar": "http://filestoresg1.beetalkmobile.com:8081/file/3802016654336628356", "name": "\u502b\u502b"}, "content": "\u90fd\u597d\u770b!\u4eba\u6b63\u7a7f\u4ec0\u9ebc\u90fd\u597d\u770b\ud83d\ude0d\ud83d\ude0d\ud83d\ude0d", "urls": [], "replies": {"first": [], "last": [], "noMoreReplies": true}, "images": [], "id": 27260168}, {"postBy": {"location": "\u53f0\u4e2d\u5e02\u00b7\u53f0\u7063", "utc": 1450357314000, "level": 0, "avatar": "http://filestoresg1.beetalkmobile.com:8081/file/-2422605645607732990", "name": "Bo Syun"}, "content": "\u6bcf\u5957\u90fd\u5f88\u597d\u770b", "urls": [], "replies": {"first": [], "last": [], "noMoreReplies": true}, "images": [], "id": 27263350}, {"postBy": {"location": "", "utc": 1450358364000, "level": 0, "avatar": "http://filestoresg1.beetalkmobile.com:8081/file/2044862932180248866", "name": "\u676f\u4e2d\u6c34\u5f71"}, "content": "\u597d\u5427\uff01\u5176\u5be6\u2026\u2026<br /><br /><br /><br />\u6211\u9019\u5957\u6bd4\u8f03\u597d\u770b", "urls": [], "replies": {"first": [], "last": [], "noMoreReplies": true}, "images": [], "id": 27264724}, {"postBy": {"location": "\u6843\u5712\u5e02\u00b7\u53f0\u7063", "utc": 1450358631000, "level": 0, "avatar": "http://filestoresg1.beetalkmobile.com:8081/file/-5157095461626116096", "name": "\u68d2\u6253\u8001\u864e\u96de\u5403\u87f2\ud83c\udf89"}, "content": "\u4eba\u6b63\u7a7f\u4ec0\u9ebc\u90fd\u597d\u770b", "urls": [], "replies": {"first": [], "last": [], "noMoreReplies": true}, "images": [], "id": 27265082}]}
