{"noMoreComments": true, "cursorEnd": 0, "id": "2049230", "comments": [{"postBy": {"location": "\u65b0\u7af9\u7e23\u00b7\u53f0\u7063", "utc": 1441332831000, "level": 0, "avatar": "http://filestoresg1.beetalkmobile.com:8081/file/-5823039967924508417", "name": "\u5f35\u5c0f\u9d28"}, "content": "\u771f\u7684", "urls": [], "replies": {"first": [], "last": [], "noMoreReplies": true}, "images": [], "id": 19534807}, {"postBy": {"location": "\u6843\u5712\u5e02\u00b7\u53f0\u7063", "utc": 1441339392000, "level": 0, "avatar": "http://filestoresg1.beetalkmobile.com:8081/file/-888013967522670079", "name": "\u9ec3\u5c0f\u9224"}, "content": "\u771f\u4e2d\u80af", "urls": [], "replies": {"first": [], "last": [], "noMoreReplies": true}, "images": [], "id": 19540036}, {"postBy": {"location": "\u5c4f\u6771\u7e23\u00b7\u53f0\u7063", "utc": 1441339583000, "level": 0, "avatar": "http://filestoresg1.beetalkmobile.com:8081/file/-7738624509010919832", "name": "\u611b\u60c5\u5224\u5b98\uff01\u4e0d\u7576\u5c40\u4e2d\u4eba\u53ea\u7576\u8046\u807d\u8005"}, "content": "\u6c34\uff0c\u7c21\u55ae\u53c8\u660e\u767d", "urls": [], "replies": {"first": [], "last": [], "noMoreReplies": true}, "images": [], "id": 19540213}]}
