{"noMoreComments": true, "cursorEnd": 0, "id": "2090015", "comments": [{"postBy": {"location": "\u82d7\u6817\u7e23\u00b7\u53f0\u7063", "utc": 1441876300000, "level": 0, "avatar": "http://filestoresg1.beetalkmobile.com:8081/file/2087393149610326437", "name": "C\u5766(\u908a\u7de3\u4eba"}, "content": "\u7cdf\u7cd5 \u770b\u4e0d\u61c2", "urls": [], "replies": {"first": [], "last": [], "noMoreReplies": true}, "images": [], "id": 19972633}, {"postBy": {"location": "\u5c4f\u6771\u7e23\u00b7\u53f0\u7063", "utc": 1441883147000, "level": 0, "avatar": "http://filestoresg1.beetalkmobile.com:8081/file/-7545371049364468837", "name": "\u6c38\u611bTFboys\u22653\u2264\u2606"}, "content": "\u6211\u6709\u5f88\u591a\u6cf3\u8863\u7167\u5594", "urls": [], "replies": {"first": [{"content": "\u6211\u6709\u5f88\u591a\u6c92\u7a7f\u6cf3\u8863\u7684", "reply": "", "id": 12653405, "name": "\u6a02."}, {"content": "\u771f\u5047>\u00a4<", "reply": "", "id": 12653482, "name": "\u6c38\u611bTFboys\u22653\u2264\u2606"}], "last": [], "noMoreReplies": true}, "images": [], "id": 19978766}, {"postBy": {"location": "\u53f0\u5317\u5e02\u00b7\u53f0\u7063", "utc": 1442031341000, "level": 0, "avatar": "http://filestoresg1.beetalkmobile.com:8081/file/3703081507493174787", "name": "\u2606\u8332\u62c9\uff1f\uff01"}, "content": "\u9019\u6a23\u55ce\uff1f", "urls": [], "replies": {"first": [], "last": [], "noMoreReplies": true}, "images": ["http://filestoresg1.beetalkmobile.com:8081/file/ffcf25b620bb70f7e40563f460998d62", "http://filestoresg1.beetalkmobile.com:8081/file/f69ca797bd9d266fd1e6270047e007ac"], "id": 20091581}, {"postBy": {"location": "\u9ad8\u96c4\u5e02\u00b7\u53f0\u7063", "utc": 1442053567000, "level": 0, "avatar": "http://filestoresg1.beetalkmobile.com:8081/file/8312384872678852968", "name": "KAI"}, "content": "\u6211\u5011\u4f86\u7814\u7a76\u770b\u770b\u5427<br />\u8056\u5149\u5f15\u5c0e\u6211\u5011\uff01", "urls": [], "replies": {"first": [{"content": "\u8acb\u554f\u9019\u662f\u4ec0\u9ebc\u52d5\u6f2b\u311a\uff1f", "reply": "", "id": 12782817, "name": "\u7121\u5fc3"}], "last": [{"content": "\u8266\u968a\u6536\u85cf", "reply": "\u7121\u5fc3", "id": 12784179, "name": "KAI"}, {"content": "\u8b1d\u8b1d", "reply": "", "id": 12919270, "name": "\u7121\u5fc3"}], "noMoreReplies": true}, "images": ["http://filestoresg1.beetalkmobile.com:8081/file/15d44711d29cbc9477841c39f4708a89"], "id": 20111757}]}
