{"noMoreComments": true, "cursorEnd": 0, "id": "2613226", "comments": [{"postBy": {"location": "\u53f0\u4e2d\u5e02\u00b7\u53f0\u7063", "utc": 1448724080000, "level": 0, "avatar": "http://filestoresg1.beetalkmobile.com:8081/file/-1731275614859202955", "name": "\u6c5f\u555f\u5b89"}, "content": "\u55e8  <br />\u8981\u4e00\u8d77\u73a9\u561b", "urls": [], "replies": {"first": [], "last": [], "noMoreReplies": true}, "images": [], "id": 25899196}, {"postBy": {"location": "\u5b9c\u862d\u7e23\u00b7\u53f0\u7063", "utc": 1448724516000, "level": 0, "avatar": "http://filestoresg1.beetalkmobile.com:8081/file/8193727790253749494", "name": "Jay"}, "content": "\u54c8\u54c8\u54c8 \u4e00\u8d77\u73a9\u554a", "urls": [], "replies": {"first": [], "last": [], "noMoreReplies": true}, "images": [], "id": 25899741}, {"postBy": {"location": "\u53f0\u5317\u5e02\u00b7\u53f0\u7063", "utc": 1448724619000, "level": 0, "avatar": "http://filestoresg1.beetalkmobile.com:8081/file/2508163045688973872", "name": "\u51f1"}, "content": "MadmanKurumi <br />\u4e00\u8d77\u73a9\u5662", "urls": [], "replies": {"first": [], "last": [], "noMoreReplies": true}, "images": [], "id": 25899871}, {"postBy": {"location": "\u5b9c\u862d\u7e23\u00b7\u53f0\u7063", "utc": 1448729087000, "level": 0, "avatar": "http://filestoresg1.beetalkmobile.com:8081/file/-2816633222262625811", "name": "wulin"}, "content": "+++", "urls": [], "replies": {"first": [], "last": [], "noMoreReplies": true}, "images": ["http://filestoresg1.beetalkmobile.com:8081/file/72a175a72d75cc9ee80b9e3ca900a699"], "id": 25904773}, {"postBy": {"location": "\u9ad8\u96c4\u5e02\u00b7\u53f0\u7063", "utc": 1448916645000, "level": 0, "avatar": "http://filestoresg1.beetalkmobile.com:8081/file/-272145613033611438", "name": "\u53ee\u5679"}, "content": "Tw.\uff08\u7a7a\u767d\uff09PT.\uff08\u7a7a\u767d\uff09YasuoGod", "urls": [], "replies": {"first": [], "last": [], "noMoreReplies": true}, "images": [], "id": 26050331}, {"postBy": {"location": "\u53f0\u5317\u5e02\u00b7\u53f0\u7063", "utc": 1448954707000, "level": 0, "avatar": "http://filestoresg1.beetalkmobile.com:8081/file/-7806159816446385563", "name": "\u03c9"}, "content": "clara\u6a3a++", "urls": [], "replies": {"first": [], "last": [], "noMoreReplies": true}, "images": [], "id": 26074195}, {"postBy": {"location": "\u82d7\u6817\u7e23\u00b7\u53f0\u7063", "utc": 1448964789000, "level": 0, "avatar": "http://filestoresg1.beetalkmobile.com:8081/file/4886253482983051249", "name": "\u9716"}, "content": "id:\u8a87\u650f\u8b00", "urls": [], "replies": {"first": [], "last": [], "noMoreReplies": true}, "images": [], "id": 26082475}, {"postBy": {"location": "\u9ad8\u96c4\u5e02\u00b7\u53f0\u7063", "utc": 1448976434000, "level": 0, "avatar": "http://filestoresg1.beetalkmobile.com:8081/file/-8561899235113240282", "name": "Eric Yu"}, "content": "\u8f14\u52a9\u80a5\u6599\u6700\u5f8c\u5e0c\u671b", "urls": [], "replies": {"first": [], "last": [], "noMoreReplies": true}, "images": [], "id": 26094916}, {"postBy": {"location": "\u5357\u6295\u7e23\u00b7\u53f0\u7063", "utc": 1448979713000, "level": 0, "avatar": "http://filestoresg1.beetalkmobile.com:8081/file/-8202013693634051618", "name": "\u923a\u6f8d(\u8fb0)"}, "content": "\u53ef\u3127\u8d77\u96f7\u6709rc\u6709\u9ea5", "urls": [], "replies": {"first": [], "last": [], "noMoreReplies": true}, "images": [], "id": 26099318}, {"postBy": {"location": "\u65b0\u5317\u5e02\u00b7\u53f0\u7063", "utc": 1448981842000, "level": 0, "avatar": "http://filestoresg1.beetalkmobile.com:8081/file/-1971452935052376828", "name": "\u963f\u8f1d"}, "content": "\u5e25\u5230\u88ab\u9b3c\u73a9<br />\u6211\u662f\u96f7\u5305", "urls": [], "replies": {"first": [], "last": [], "noMoreReplies": true}, "images": [], "id": 26102237}]}
