{"noMoreComments": true, "cursorEnd": 0, "id": "2644030", "comments": [{"postBy": {"location": "\u96f2\u6797\u7e23\u00b7\u53f0\u7063", "utc": 1449147399000, "level": 0, "avatar": "http://filestoresg1.beetalkmobile.com:8081/file/-3327533401936673009", "name": "Pitiod Mo"}, "content": "\u6f02\u4eae\u5594 \ud83d\udc4d\ud83c\udffb", "urls": [], "replies": {"first": [], "last": [], "noMoreReplies": true}, "images": [], "id": 26229095}, {"postBy": {"location": "\u96f2\u6797\u7e23\u00b7\u53f0\u7063", "utc": 1449756537000, "level": 0, "avatar": "http://filestoresg1.beetalkmobile.com:8081/file/8080297765131628033", "name": "\u963f\u582f"}, "content": "\u53ef\u4ee5\u5e6b\u6211\u7528\u55ce\uff1f\uff01", "urls": [], "replies": {"first": [{"content": "\u5982\u679c\u51fa\u53bb\u4e0d\u6015\u88ab\u7b11\u7684\u8a71", "reply": "", "id": 17051944, "name": "coco"}, {"content": "\u89ba\u5f97\u597d\u6709\u6311\u6230\uff0c\u54c8\u54c8", "reply": "", "id": 17052870, "name": "\u963f\u582f"}], "last": [], "noMoreReplies": true}, "images": [], "id": 26741037}]}
